odoo10_addon_shopinvader_pending_cart_reminder-10.0.1.1.0-nspkg.pth
odoo/addons/shopinvader_pending_cart_reminder/README.rst
odoo/addons/shopinvader_pending_cart_reminder/__init__.py
odoo/addons/shopinvader_pending_cart_reminder/__manifest__.py
odoo/addons/shopinvader_pending_cart_reminder/data/ir_cron.xml
odoo/addons/shopinvader_pending_cart_reminder/data/mail_template.xml
odoo/addons/shopinvader_pending_cart_reminder/models/__init__.py
odoo/addons/shopinvader_pending_cart_reminder/models/sale_order.py
odoo/addons/shopinvader_pending_cart_reminder/models/shopinvader_backend.py
odoo/addons/shopinvader_pending_cart_reminder/readme/CONTRIBUTORS.rst
odoo/addons/shopinvader_pending_cart_reminder/readme/DESCRIPTION.rst
odoo/addons/shopinvader_pending_cart_reminder/readme/USAGE.rst
odoo/addons/shopinvader_pending_cart_reminder/static/description/index.html
odoo/addons/shopinvader_pending_cart_reminder/tests/__init__.py
odoo/addons/shopinvader_pending_cart_reminder/tests/test_sale_order.py
odoo/addons/shopinvader_pending_cart_reminder/tests/test_shopinvader_backend.py
odoo/addons/shopinvader_pending_cart_reminder/views/shopinvader_backend.xml
odoo10_addon_shopinvader_pending_cart_reminder-10.0.1.1.0.dist-info/METADATA
odoo10_addon_shopinvader_pending_cart_reminder-10.0.1.1.0.dist-info/WHEEL
odoo10_addon_shopinvader_pending_cart_reminder-10.0.1.1.0.dist-info/namespace_packages.txt
odoo10_addon_shopinvader_pending_cart_reminder-10.0.1.1.0.dist-info/top_level.txt
odoo10_addon_shopinvader_pending_cart_reminder-10.0.1.1.0.dist-info/RECORD
